cirm_odm/__init__.py
cirm_odm/cpe_model.py
cirm_odm/cve_processing_results.py
cirm_odm/cves.py
cirm_odm/cwes.py
cirm_odm/known_cpes.py
cirm_odm-0.1.7.dist-info/WHEEL
cirm_odm-0.1.7.dist-info/METADATA
cirm_odm-0.1.7.dist-info/RECORD
