Metadata-Version: 2.4
Name: cirm-odm
Version: 0.1.7
Summary: ODM models for CVE, CWE, and CPE management
Author: CyberSecurity S.r.l.
Requires-Python: >=3.8
Classifier: Development Status :: 3 - Alpha
Classifier: Programming Language :: Python :: 3.11
Requires-Dist: beanie>=1.21.0
Requires-Dist: motor>=3.2.0
Requires-Dist: pydantic>=2.0.0
Project-URL: Documentation, https://github.com/cybersecurity-srl/cirm-odm/blob/main/README.md
Project-URL: Source, https://github.com/cybersecurity-srl/cirm-odm/tree/main
